HitoAI_SusNet/__init__.py
HitoAI_SusNet/ann_activator.py
hitoai_susnet-0.3.0.dist-info/METADATA
hitoai_susnet-0.3.0.dist-info/WHEEL
hitoai_susnet-0.3.0.dist-info/RECORD
