Metadata-Version: 2.1
Name: HitoAI_SusNet
Version: 0.3.0
Summary: A project to predict temperature using an Artificial Neural Network.
License: MIT
Author: Shenal Elekuttige
Author-email: shenaal.h@hitoai.ai
Requires-Python: >=3.8,<4.0
Classifier: License :: OSI Approved :: MIT License
Classifier: Programming Language :: Python :: 3
Classifier: Programming Language :: Python :: 3.8
Classifier: Programming Language :: Python :: 3.9
Classifier: Programming Language :: Python :: 3.10
Classifier: Programming Language :: Python :: 3.11
Classifier: Programming Language :: Python :: 3.12
Requires-Dist: keras (>=2.3.0,<3.0.0)
Requires-Dist: numpy (>=1.18.0,<2.0.0)
Requires-Dist: pandas (>=1.0.0,<2.0.0)
Requires-Dist: scikit-learn (>=0.22.0,<0.23.0)
Requires-Dist: tensorflow (>=2.0.0,<3.0.0)
